addr_detector/Fasttext_clf.py
addr_detector/__init__.py
addr_detector/addr_detector.py
addr_detector/postal_clf.py
addr_detector/voting_model.py
addr_detector/model/__init__.py
addr_detector/model/ft_ad.ftz
addr_detector-0.1.0.data/data/model/model.ftz
addr_detector-0.1.0.dist-info/DESCRIPTION.rst
addr_detector-0.1.0.dist-info/METADATA
addr_detector-0.1.0.dist-info/RECORD
addr_detector-0.1.0.dist-info/WHEEL
addr_detector-0.1.0.dist-info/metadata.json
addr_detector-0.1.0.dist-info/top_level.txt
data/__init__.py
data/model.ftz
tests/__init__.py
tests/test_addr_detector.py
