Metadata-Version: 2.0
Name: addr-detector
Version: 0.1.0
Summary: Python address detector 
Home-page: https://github.com/rdoume/addr_detector
Author: Qwant
Author-email: robin@qwantresearch.com
License: GNU General Public License v3
Keywords: addr_detector
Platform: UNKNOWN
Classifier: Development Status :: 2 - Pre-Alpha
Classifier: Intended Audience :: Developers
Classifier: License :: OSI Approved :: GNU General Public License v3 (GPLv3)
Classifier: Natural Language :: English
Classifier: Programming Language :: Python :: 2
Classifier: Programming Language :: Python :: 2.6
Classifier: Programming Language :: Python :: 2.7
Classifier: Programming Language :: Python :: 3
Classifier: Programming Language :: Python :: 3.3
Classifier: Programming Language :: Python :: 3.4
Classifier: Programming Language :: Python :: 3.5
Classifier: Programming Language :: Python :: 3.6
Requires-Dist: Cython
Requires-Dist: Sphinx
Requires-Dist: click
Requires-Dist: coverage
Requires-Dist: cysignals
Requires-Dist: flake8
Requires-Dist: future
Requires-Dist: postal (==1.0)
Requires-Dist: pyfasttext
Requires-Dist: python-dotenv (>=0.5.1)
Requires-Dist: scikit-learn (==0.19.0)
